recent_items_list/__init__.py
recent_items_list-1.1.2.dist-info/LICENSE
recent_items_list-1.1.2.dist-info/WHEEL
recent_items_list-1.1.2.dist-info/METADATA
recent_items_list-1.1.2.dist-info/RECORD
