Metadata-Version: 2.1
Name: recent_items_list
Version: 1.1.2
Summary: RecentItemsList acts like a list, except that calling the "bump()" method on it
Author-email: Leon Dionne <ldionne@dridesign.sh.cn>
Classifier: License :: OSI Approved :: GNU General Public License v3 or later (GPLv3+)
Classifier: Programming Language :: Python
Classifier: Programming Language :: Python :: 3.10
Classifier: Intended Audience :: Developers
Project-URL: Home, https://github.com/Zen-Master-SoSo/recent_items_list
